prom.py
pygments_prometheus-1.0.dist-info/DESCRIPTION.rst
pygments_prometheus-1.0.dist-info/METADATA
pygments_prometheus-1.0.dist-info/RECORD
pygments_prometheus-1.0.dist-info/WHEEL
pygments_prometheus-1.0.dist-info/entry_points.txt
pygments_prometheus-1.0.dist-info/metadata.json
pygments_prometheus-1.0.dist-info/top_level.txt
pygments_prometheus-1.0.dist-info/zip-safe
