Metadata-Version: 2.0
Name: pygments-prometheus
Version: 1.0
Summary: Pygments lexer for prometheus metrics
Home-page: https://github.com/giganteous/pygments-prometheus
Author: Kai Storbeck
Author-email: kai@xs4all.nl
License: BSD
Keywords: pygments prometheus
Platform: UNKNOWN
Classifier: Development Status :: 3 - Alpha
Classifier: Environment :: Plugins
Classifier: Intended Audience :: Developers
Classifier: License :: OSI Approved :: BSD License
Classifier: Operating System :: OS Independent
Classifier: Programming Language :: Python :: 3
Requires-Dist: setuptools
Requires-Dist: pygments
